{
  "system": {
    "location": {
      "site": "TW-NTC-TPKD",
      "section": "NTC-TPKD",
      "position": {
        "x": 0,
        "y": 0
      }
    },
    "physical_tag": {
      "asset": {
        "site": "TW-NTC-TPKD",
        "name": "LT-4257",
        "guid": "uuid://d3fe520c-04c3-4b2f-8ace-8949892e43e3"
      }
    }
  },
  "pointset": {
    "points": {
      "dimmer_percentage_command": {
        "units": "Percent"
      }
    }
  },
  "gateway": {
    "gateway_id": "LTGW-28"
  },
  "version": 1,
  "timestamp": "2021-10-13T14:32:47.3438361+01:00"
}