{
  "system": {
    "location": {
      "site": "TW-NTC-TPKD",
      "section": "NTC-TPKD",
      "position": {
        "x": 0,
        "y": 0
      }
    },
    "physical_tag": {
      "asset": {
        "site": "TW-NTC-TPKD",
        "name": "LKP-234",
        "guid": "uuid://c46ca891-e6fd-46ed-a7c2-3d9ccacfbe0e"
      }
    }
  },
  "pointset": {
    "points": {
      "zone_scene_command": {
        "units": "No-units"
      },
      "brightness_percentage_command": {
        "units": "Percent"
      },
      "scene_command": {
        "units": "No-units"
      }
    }
  },
  "gateway": {
    "gateway_id": "LTGW-30"
  },
  "version": 1,
  "timestamp": "2021-10-13T14:32:47.4008598+01:00"
}