{
  "system": {
    "location": {
      "site": "TW-NTC-TPKD",
      "section": "NTC-TPKD",
      "position": {
        "x": 0,
        "y": 0
      }
    },
    "physical_tag": {
      "asset": {
        "site": "TW-NTC-TPKD",
        "name": "LT-2057",
        "guid": "uuid://0a0da0a5-a52a-4ec8-a02d-e12fcb348429"
      }
    }
  },
  "pointset": {
    "points": {
      "dimmer_percentage_command": {
        "units": "Percent"
      }
    }
  },
  "gateway": {
    "gateway_id": "LTGW-19"
  },
  "version": 1,
  "timestamp": "2021-10-13T14:32:47.1019655+01:00"
}