{
  "system": {
    "location": {
      "site": "TW-NTC-TPKD",
      "section": "NTC-TPKD",
      "position": {
        "x": 0,
        "y": 0
      }
    },
    "physical_tag": {
      "asset": {
        "site": "TW-NTC-TPKD",
        "name": "LT-2059",
        "guid": "uuid://d7667a1d-18bc-4e9e-9216-2728f5d22438"
      }
    }
  },
  "pointset": {
    "points": {
      "dimmer_percentage_command": {
        "units": "Percent"
      }
    }
  },
  "gateway": {
    "gateway_id": "LTGW-19"
  },
  "version": 1,
  "timestamp": "2021-10-13T14:32:47.1021136+01:00"
}