{
  "system": {
    "location": {
      "site": "TW-NTC-TPKD",
      "section": "NTC-TPKD",
      "position": {
        "x": 0,
        "y": 0
      }
    },
    "physical_tag": {
      "asset": {
        "site": "TW-NTC-TPKD",
        "name": "LT-1123",
        "guid": "uuid://3ebe69ab-5bbc-4e72-8cac-a8afbb7ccdc3"
      }
    }
  },
  "pointset": {
    "points": {
      "dimmer_percentage_command": {
        "units": "Percent"
      }
    }
  },
  "gateway": {
    "gateway_id": "LTGW-14"
  },
  "version": 1,
  "timestamp": "2021-10-13T14:32:46.9710065+01:00"
}