{
  "system": {
    "location": {
      "site": "TW-NTC-TPKD",
      "section": "NTC-TPKD",
      "position": {
        "x": 0,
        "y": 0
      }
    },
    "physical_tag": {
      "asset": {
        "site": "TW-NTC-TPKD",
        "name": "LT-5638",
        "guid": "uuid://fed0feb9-b066-4bd3-a8e0-2c73e626b29c"
      }
    }
  },
  "pointset": {
    "points": {
      "dimmer_percentage_command": {
        "units": "Percent"
      }
    }
  },
  "gateway": {
    "gateway_id": "LTGW-7"
  },
  "version": 1,
  "timestamp": "2021-10-13T14:32:47.4902095+01:00"
}