{
  "system": {
    "location": {
      "site": "TW-NTC-TPKD",
      "section": "NTC-TPKD",
      "position": {
        "x": 0,
        "y": 0
      }
    },
    "physical_tag": {
      "asset": {
        "site": "TW-NTC-TPKD",
        "name": "LKP-31",
        "guid": "uuid://441ee6d9-c8c8-4ade-bc7b-fab36b219c41"
      }
    }
  },
  "pointset": {
    "points": {
      "zone_scene_command": {
        "units": "No-units"
      },
      "brightness_percentage_command": {
        "units": "Percent"
      },
      "scene_command": {
        "units": "No-units"
      }
    }
  },
  "gateway": {
    "gateway_id": "LTGW-1"
  },
  "version": 1,
  "timestamp": "2021-10-13T14:32:46.8202817+01:00"
}