{
  "system": {
    "location": {
      "site": "TW-NTC-TPKD",
      "section": "NTC-TPKD",
      "position": {
        "x": 0,
        "y": 0
      }
    },
    "physical_tag": {
      "asset": {
        "site": "TW-NTC-TPKD",
        "name": "LT-4505",
        "guid": "uuid://136eb3f3-a4d5-4bf8-a5ec-9cd131d87dff"
      }
    }
  },
  "pointset": {
    "points": {
      "dimmer_percentage_command": {
        "units": "Percent"
      }
    }
  },
  "gateway": {
    "gateway_id": "LTGW-30"
  },
  "version": 1,
  "timestamp": "2021-10-13T14:32:47.3814593+01:00"
}