{
  "system": {
    "location": {
      "site": "TW-NTC-TPKD",
      "section": "NTC-TPKD",
      "position": {
        "x": 0,
        "y": 0
      }
    },
    "physical_tag": {
      "asset": {
        "site": "TW-NTC-TPKD",
        "name": "LGRP-86",
        "guid": "uuid://7d089f9c-cf2f-499f-a27f-50ff8cc67048"
      }
    }
  },
  "pointset": {
    "points": {
      "brightness_percentage_command": {
        "units": "Percent"
      }
    }
  },
  "gateway": {
    "gateway_id": "LTGW-1"
  },
  "version": 1,
  "timestamp": "2021-10-13T14:32:46.8178105+01:00"
}