{
  "system": {
    "location": {
      "site": "TW-NTC-TPKD",
      "section": "NTC-TPKD",
      "position": {
        "x": 0,
        "y": 0
      }
    },
    "physical_tag": {
      "asset": {
        "site": "TW-NTC-TPKD",
        "name": "LGRP-348",
        "guid": "uuid://f732b806-e9f9-4166-b0e8-9f89eaaec6ae"
      }
    }
  },
  "pointset": {
    "points": {
      "brightness_percentage_command": {
        "units": "Percent"
      }
    }
  },
  "gateway": {
    "gateway_id": "LTGW-18"
  },
  "version": 1,
  "timestamp": "2021-10-13T14:32:47.0853275+01:00"
}