{
  "system": {
    "location": {
      "site": "TW-NTC-TPKD",
      "section": "NTC-TPKD",
      "position": {
        "x": 0,
        "y": 0
      }
    },
    "physical_tag": {
      "asset": {
        "site": "TW-NTC-TPKD",
        "name": "LKP-211",
        "guid": "uuid://8f24957e-9764-4290-ac86-cea1f22bb54b"
      }
    }
  },
  "pointset": {
    "points": {
      "zone_scene_command": {
        "units": "No-units"
      },
      "brightness_percentage_command": {
        "units": "Percent"
      },
      "scene_command": {
        "units": "No-units"
      }
    }
  },
  "gateway": {
    "gateway_id": "LTGW-28"
  },
  "version": 1,
  "timestamp": "2021-10-13T14:32:47.3305003+01:00"
}