{
  "system": {
    "location": {
      "site": "TW-NTC-TPKD",
      "section": "NTC-TPKD",
      "position": {
        "x": 0,
        "y": 0
      }
    },
    "physical_tag": {
      "asset": {
        "site": "TW-NTC-TPKD",
        "name": "LMS-524",
        "guid": "uuid://87c19ea5-95cf-433e-b43d-74c74fb08ddc"
      }
    }
  },
  "pointset": {
    "points": {
      "zone_occupancy_status": {
        "units": "No-units"
      }
    }
  },
  "gateway": {
    "gateway_id": "LTGW-21"
  },
  "version": 1,
  "timestamp": "2021-10-13T14:32:47.1955066+01:00"
}