{
  "system": {
    "location": {
      "site": "TW-NTC-TPKD",
      "section": "NTC-TPKD",
      "position": {
        "x": 0,
        "y": 0
      }
    },
    "physical_tag": {
      "asset": {
        "site": "TW-NTC-TPKD",
        "name": "LKP-279",
        "guid": "uuid://aae0e91f-771b-4ab3-a968-1279601773be"
      }
    }
  },
  "pointset": {
    "points": {
      "zone_scene_command": {
        "units": "No-units"
      },
      "brightness_percentage_command": {
        "units": "Percent"
      },
      "scene_command": {
        "units": "No-units"
      }
    }
  },
  "gateway": {
    "gateway_id": "LTGW-6"
  },
  "version": 1,
  "timestamp": "2021-10-13T14:32:47.4775677+01:00"
}