{
  "system": {
    "location": {
      "site": "TW-NTC-TPKD",
      "section": "NTC-TPKD",
      "position": {
        "x": 0,
        "y": 0
      }
    },
    "physical_tag": {
      "asset": {
        "site": "TW-NTC-TPKD",
        "name": "LT-3580",
        "guid": "uuid://4861e8e2-0f2b-4e0b-87be-bbc096c8b3d6"
      }
    }
  },
  "pointset": {
    "points": {
      "dimmer_percentage_command": {
        "units": "Percent"
      }
    }
  },
  "gateway": {
    "gateway_id": "LTGW-25"
  },
  "version": 1,
  "timestamp": "2021-10-13T14:32:47.2774023+01:00"
}