{
  "system": {
    "location": {
      "site": "TW-NTC-TPKD",
      "section": "NTC-TPKD",
      "position": {
        "x": 0,
        "y": 0
      }
    },
    "physical_tag": {
      "asset": {
        "site": "TW-NTC-TPKD",
        "name": "LT-870",
        "guid": "uuid://910dca25-0d23-49cd-891a-bc61a0207fae"
      }
    }
  },
  "pointset": {
    "points": {
      "dimmer_percentage_command": {
        "units": "Percent"
      }
    }
  },
  "gateway": {
    "gateway_id": "LTGW-13"
  },
  "version": 1,
  "timestamp": "2021-10-13T14:32:46.9361444+01:00"
}