{
  "system": {
    "location": {
      "site": "TW-NTC-TPKD",
      "section": "NTC-TPKD",
      "position": {
        "x": 0,
        "y": 0
      }
    },
    "physical_tag": {
      "asset": {
        "site": "TW-NTC-TPKD",
        "name": "LT-3927",
        "guid": "uuid://d4affec6-afba-45e8-b5d0-c9b36d9e681c"
      }
    }
  },
  "pointset": {
    "points": {
      "dimmer_percentage_command": {
        "units": "Percent"
      }
    }
  },
  "gateway": {
    "gateway_id": "LTGW-27"
  },
  "version": 1,
  "timestamp": "2021-10-13T14:32:47.3113674+01:00"
}