{
  "system": {
    "location": {
      "site": "TW-NTC-TPKD",
      "section": "NTC-TPKD",
      "position": {
        "x": 0,
        "y": 0
      }
    },
    "physical_tag": {
      "asset": {
        "site": "TW-NTC-TPKD",
        "name": "LT-4852",
        "guid": "uuid://94e874e5-b035-4a70-a729-bc5b74dbbe5d"
      }
    }
  },
  "pointset": {
    "points": {
      "dimmer_percentage_command": {
        "units": "Percent"
      }
    }
  },
  "gateway": {
    "gateway_id": "LTGW-31"
  },
  "version": 1,
  "timestamp": "2021-10-13T14:32:47.4050468+01:00"
}