{
  "system": {
    "location": {
      "site": "TW-NTC-TPKD",
      "section": "NTC-TPKD",
      "position": {
        "x": 0,
        "y": 0
      }
    },
    "physical_tag": {
      "asset": {
        "site": "TW-NTC-TPKD",
        "name": "LT-3420",
        "guid": "uuid://792e1fcd-08b4-4dbf-826b-d49a6eabda51"
      }
    }
  },
  "pointset": {
    "points": {
      "dimmer_percentage_command": {
        "units": "Percent"
      }
    }
  },
  "gateway": {
    "gateway_id": "LTGW-24"
  },
  "version": 1,
  "timestamp": "2021-10-13T14:32:47.2601489+01:00"
}