{
  "system": {
    "location": {
      "site": "TW-NTC-TPKD",
      "section": "NTC-TPKD",
      "position": {
        "x": 0,
        "y": 0
      }
    },
    "physical_tag": {
      "asset": {
        "site": "TW-NTC-TPKD",
        "name": "LMS-755",
        "guid": "uuid://0838f58c-42f6-47d0-ad3f-9a46d1e6d48f"
      }
    }
  },
  "pointset": {
    "points": {
      "zone_occupancy_status": {
        "units": "No-units"
      }
    }
  },
  "gateway": {
    "gateway_id": "LTGW-27"
  },
  "version": 1,
  "timestamp": "2021-10-13T14:32:47.3192007+01:00"
}