{
  "system": {
    "location": {
      "site": "TW-NTC-TPKD",
      "section": "NTC-TPKD",
      "position": {
        "x": 0,
        "y": 0
      }
    },
    "physical_tag": {
      "asset": {
        "site": "TW-NTC-TPKD",
        "name": "LT-4648",
        "guid": "uuid://c3fd47af-21b6-4c93-a1eb-c2994cb74630"
      }
    }
  },
  "pointset": {
    "points": {
      "dimmer_percentage_command": {
        "units": "Percent"
      }
    }
  },
  "gateway": {
    "gateway_id": "LTGW-30"
  },
  "version": 1,
  "timestamp": "2021-10-13T14:32:47.3940462+01:00"
}