{
  "timestamp" : "2024-12-03T10:06:13Z",
  "version" : "1.5.2",
  "cloud" : {
    "resource_type" : "DEVICE"
  },
  "system" : {
    "tags" : [ ],
    "location" : {
      "site" : "TW-NTC-TPKD"
    },
    "min_loglevel" : 300
  },
  "gateway" : {
    "gateway_id" : "CGW-98"
  },
  "localnet" : {
    "families" : {
      "iot" : {
        "addr" : "EM-106"
      }
    }
  },
  "testing" : {
    "nostate" : true,
    "targets" : {
      "applied" : {
        "target_point" : "em_106_power_sensor",
        "target_value" : 98
      },
      "invalid" : {
        "target_point" : "em_106_power_sensor",
        "target_value" : [ ]
      }
    }
  },
  "features" : {
    "system" : {
      "stage" : "alpha"
    },
    "writeback" : {
      "stage" : "alpha"
    },
    "pointset" : {
      "stage" : "alpha"
    }
  },
  "pointset" : {
    "points" : {
      "em_106_power_sensor" : {
        "units" : "",
        "writable" : true,
        "ref" : "13867",
        "tags" : [ ]
      },
      "em_106_powerfactor_sensor" : {
        "units" : "",
        "writable" : true,
        "ref" : "13869",
        "tags" : [ ]
      },
      "em_106_phase2_line_current_sensor" : {
        "units" : "",
        "writable" : true,
        "ref" : "13862",
        "tags" : [ ]
      },
      "em_106_reactive_power_sensor" : {
        "units" : "",
        "writable" : true,
        "ref" : "13870",
        "tags" : [ ]
      },
      "em_106_line_frequency_sensor" : {
        "units" : "",
        "writable" : true,
        "ref" : "13871",
        "tags" : [ ]
      },
      "em_106_phase1_line_current_sensor" : {
        "units" : "",
        "writable" : true,
        "ref" : "13861",
        "tags" : [ ]
      },
      "em_106_energy_accumulator" : {
        "units" : "",
        "writable" : true,
        "ref" : "13868",
        "tags" : [ ]
      },
      "em_106_phase3_neutral_line_voltage_sensor" : {
        "units" : "",
        "writable" : true,
        "ref" : "13866",
        "tags" : [ ]
      },
      "em_106_phase1_neutral_line_voltage_sensor" : {
        "units" : "",
        "writable" : true,
        "ref" : "13864",
        "tags" : [ ]
      },
      "em_106_phase3_line_current_sensor" : {
        "units" : "",
        "writable" : true,
        "ref" : "13863",
        "tags" : [ ]
      },
      "em_106_phase2_neutral_line_voltage_sensor" : {
        "units" : "",
        "writable" : true,
        "ref" : "13865",
        "tags" : [ ]
      }
    }
  }
}